pyannote.generators-2.0-py3.6-nspkg.pth
pyannote/generators/__init__.py
pyannote/generators/_version.py
pyannote/generators/background.py
pyannote/generators/batch.py
pyannote/generators/buffer.py
pyannote/generators/fragment.py
pyannote/generators/indices.py
pyannote.generators-2.0.dist-info/METADATA
pyannote.generators-2.0.dist-info/RECORD
pyannote.generators-2.0.dist-info/WHEEL
pyannote.generators-2.0.dist-info/namespace_packages.txt
pyannote.generators-2.0.dist-info/pbr.json
pyannote.generators-2.0.dist-info/top_level.txt
