Metadata-Version: 2.1
Name: pyannote.generators
Version: 2.0
Summary: itertools for pyannote
Home-page: http://herve.niderb.fr/
Author: Hervé Bredin
Author-email: bredin@limsi.fr
License: UNKNOWN
Platform: UNKNOWN
Classifier: Development Status :: 4 - Beta
Classifier: Intended Audience :: Science/Research
Classifier: License :: OSI Approved :: MIT License
Classifier: Natural Language :: English
Classifier: Programming Language :: Python :: 3
Classifier: Programming Language :: Python :: 3.6
Classifier: Programming Language :: Python :: 3.7
Classifier: Topic :: Scientific/Engineering
Requires-Dist: pyannote.core (>=1.4.1)
Requires-Dist: pyannote.database (>=1.5.4)
